code2docs_cli/__init__.py
code2docs_cli/main.py
code2docs_cli/utils/__init__.py
code2docs_cli/utils/file_processes.py
code2docs_cli/utils/parsers.py
code2docs_cli/utils/prompt_templates.py
code2docs_cli/utils/rag.py
code2docs_cli/utils/scan.py
code2docs_cli/utils/tasks.py
code2docs_cli-1.3.1.dist-info/METADATA
code2docs_cli-1.3.1.dist-info/WHEEL
code2docs_cli-1.3.1.dist-info/entry_points.txt
code2docs_cli-1.3.1.dist-info/RECORD
