Metadata-Version: 2.1
Name: code2docs-cli
Version: 1.3.1
Summary: Code2Docs: An AI-powered, open source CLI tool for generating inline code documentation, API references, database schema docs, and project READMEs from your codebase.
Author: xKarinSan
Author-email: setsunayukii88@gmail.com
Requires-Python: >=3.12,<4.0
Classifier: Programming Language :: Python :: 3
Classifier: Programming Language :: Python :: 3.12
Requires-Dist: langchain (==0.3.23)
Requires-Dist: langchain-openai (==0.3.12)
Requires-Dist: openai (==1.73.0)
Requires-Dist: pathspec (==0.12.1)
Requires-Dist: python-dotenv (==1.1.0)
Requires-Dist: rich (==14.0.0)
Requires-Dist: typer (==0.15.2)
